WaterDetect.ini
runWaterDetect.py
waterdetect/Common.py
waterdetect/External_mask.py
waterdetect/Glint.py
waterdetect/Image.py
waterdetect/InputOutput.py
waterdetect/WaterDetect.py
waterdetect/__init__.py
waterdetect-1.5.15.dist-info/LICENSE
waterdetect-1.5.15.dist-info/METADATA
waterdetect-1.5.15.dist-info/WHEEL
waterdetect-1.5.15.dist-info/entry_points.txt
waterdetect-1.5.15.dist-info/top_level.txt
waterdetect-1.5.15.dist-info/RECORD
